[{"prefix":"/admin/base/comm","name":"","api":[{"method":"post","path":"/personUpdate"},{"method":"get","path":"/uploadMode"},{"method":"get","path":"/permmenu"},{"method":"get","path":"/person"},{"method":"post","path":"/upload"},{"method":"post","path":"/logout"}]},{"prefix":"/admin/base/open","name":"","api":[{"method":"get","path":"/refreshToken"},{"method":"get","path":"/captcha"},{"method":"post","path":"/login"},{"method":"get","path":"/html"},{"method":"get","path":"/eps"}]},{"prefix":"/admin/base/sys/department","name":"BaseSysDepartmentEntity","api":[{"method":"post","path":"/delete"},{"method":"post","path":"/update"},{"method":"post","path":"/order"},{"method":"post","path":"/list"},{"method":"post","path":"/add"}]},{"prefix":"/admin/base/sys/log","name":"BaseSysLogEntity","api":[{"method":"post","path":"/setKeep"},{"method":"get","path":"/getKeep"},{"method":"post","path":"/clear"},{"method":"post","path":"/page"}]},{"prefix":"/admin/base/sys/menu","name":"BaseSysMenuEntity","api":[{"method":"post","path":"/create"},{"method":"post","path":"/export"},{"method":"post","path":"/import"},{"method":"post","path":"/delete"},{"method":"post","path":"/update"},{"method":"post","path":"/parse"},{"method":"get","path":"/info"},{"method":"post","path":"/list"},{"method":"post","path":"/page"},{"method":"post","path":"/add"}]},{"prefix":"/admin/base/sys/param","name":"BaseSysParamEntity","api":[{"method":"post","path":"/delete"},{"method":"post","path":"/update"},{"method":"get","path":"/html"},{"method":"get","path":"/info"},{"method":"post","path":"/page"},{"method":"post","path":"/add"}]},{"prefix":"/admin/base/sys/role","name":"BaseSysRoleEntity","api":[{"method":"post","path":"/delete"},{"method":"post","path":"/update"},{"method":"get","path":"/info"},{"method":"post","path":"/list"},{"method":"post","path":"/page"},{"method":"post","path":"/add"}]},{"prefix":"/admin/base/sys/user","name":"BaseSysUserEntity","api":[{"method":"get","path":"/getPageConfig"},{"method":"post","path":"/setPageConfig"},{"method":"post","path":"/delete"},{"method":"post","path":"/update"},{"method":"post","path":"/move"},{"method":"get","path":"/info"},{"method":"post","path":"/list"},{"method":"post","path":"/page"},{"method":"post","path":"/add"}]},{"prefix":"/admin/cloud/db","name":"CloudDBEntity","api":[{"method":"post","path":"/initEntity"},{"method":"post","path":"/delete"},{"method":"post","path":"/update"},{"method":"post","path":"/data"},{"method":"get","path":"/info"},{"method":"post","path":"/list"},{"method":"post","path":"/page"},{"method":"post","path":"/add"}]},{"prefix":"/admin/cloud/func/info","name":"CloudFuncInfoEntity","api":[{"method":"post","path":"/invoke"},{"method":"post","path":"/delete"},{"method":"post","path":"/update"},{"method":"get","path":"/info"},{"method":"post","path":"/list"},{"method":"post","path":"/page"},{"method":"post","path":"/add"}]},{"prefix":"/admin/cloud/func/log","name":"CloudFuncLogEntity","api":[{"method":"post","path":"/delete"},{"method":"post","path":"/update"},{"method":"get","path":"/info"},{"method":"post","path":"/list"},{"method":"post","path":"/page"},{"method":"post","path":"/add"}]},{"prefix":"/admin/demo/goods","name":"DemoGoodsEntity","api":[{"method":"post","path":"/delete"},{"method":"post","path":"/update"},{"method":"get","path":"/info"},{"method":"post","path":"/list"},{"method":"post","path":"/page"},{"method":"post","path":"/add"}]},{"prefix":"/admin/dict/info","name":"DictInfoEntity","api":[{"method":"post","path":"/delete"},{"method":"post","path":"/update"},{"method":"post","path":"/data"},{"method":"get","path":"/info"},{"method":"post","path":"/list"},{"method":"post","path":"/page"},{"method":"post","path":"/add"}]},{"prefix":"/admin/dict/type","name":"DictTypeEntity","api":[{"method":"post","path":"/delete"},{"method":"post","path":"/update"},{"method":"get","path":"/info"},{"method":"post","path":"/list"},{"method":"post","path":"/page"},{"method":"post","path":"/add"}]},{"prefix":"/admin/image/album","name":"ImageAlbumEntity","api":[{"method":"post","path":"/delete"},{"method":"post","path":"/update"},{"method":"get","path":"/info"},{"method":"post","path":"/list"},{"method":"post","path":"/page"},{"method":"post","path":"/add"}]},{"prefix":"/admin/image/Album","name":"","api":[{"method":"post","path":"/getImage"}]},{"prefix":"/admin/image/image","name":"ImageBaseData","api":[{"method":"post","path":"/delete"},{"method":"post","path":"/update"},{"method":"get","path":"/info"},{"method":"post","path":"/list"},{"method":"post","path":"/page"},{"method":"post","path":"/add"}]},{"prefix":"/admin/image/File","name":"","api":[{"method":"get","path":"/v3/3rd/users"},{"method":"post","path":"/image"},{"method":"get","path":"/image"},{"method":"post","path":"/image"},{"method":"post","path":"/image"},{"method":"get","path":"/getImageInfo"}]},{"prefix":"/admin/image/tags","name":"ImagesTagsBaseData","api":[{"method":"post","path":"/delete"},{"method":"post","path":"/update"},{"method":"get","path":"/info"},{"method":"post","path":"/list"},{"method":"post","path":"/page"},{"method":"post","path":"/add"}]},{"prefix":"/admin/iot/device","name":"IotDeviceEntity","api":[{"method":"post","path":"/searchByName"},{"method":"post","path":"/delete"},{"method":"post","path":"/update"},{"method":"get","path":"/info"},{"method":"post","path":"/list"},{"method":"post","path":"/page"},{"method":"post","path":"/add"}]},{"prefix":"/admin/iot/iot","name":"IotInfoEntity","api":[{"method":"post","path":"/registerIot"},{"method":"post","path":"/delete"},{"method":"post","path":"/list"},{"method":"post","path":"/add"},{"method":"post","path":"getIotInfo"},{"method":"post","path":"/add"}]},{"prefix":"/admin/iot/message","name":"IotMessageEntity","api":[{"method":"post","path":"/page"}]},{"prefix":"/admin/iot/mqtt","name":"","api":[{"method":"post","path":"/publish"},{"method":"get","path":"/config"},{"method":"get","path":"/config"}]},{"prefix":"/admin/recycle/data","name":"RecycleDataEntity","api":[{"method":"post","path":"/restore"},{"method":"get","path":"/info"},{"method":"post","path":"/page"}]},{"prefix":"/admin/schedule/schedule","name":"ScheduleEntity","api":[{"method":"post","path":"/delete"},{"method":"post","path":"/update"},{"method":"get","path":"/info"},{"method":"post","path":"/list"},{"method":"post","path":"/page"},{"method":"post","path":"/add"}]},{"prefix":"/admin/space/info","name":"SpaceInfoEntity","api":[{"method":"get","path":"/getConfig"},{"method":"post","path":"/delete"},{"method":"post","path":"/update"},{"method":"get","path":"/info"},{"method":"post","path":"/list"},{"method":"post","path":"/page"},{"method":"post","path":"/add"}]},{"prefix":"/admin/space/type","name":"SpaceTypeEntity","api":[{"method":"post","path":"/delete"},{"method":"post","path":"/update"},{"method":"get","path":"/info"},{"method":"post","path":"/list"},{"method":"post","path":"/page"},{"method":"post","path":"/add"}]},{"prefix":"/admin/task/info","name":"TaskInfoEntity","api":[{"method":"post","path":"/delete"},{"method":"post","path":"/update"},{"method":"post","path":"/start"},{"method":"post","path":"/once"},{"method":"post","path":"/stop"},{"method":"get","path":"/info"},{"method":"post","path":"/page"},{"method":"get","path":"/log"},{"method":"post","path":"/add"}]},{"prefix":"/admin/user/info","name":"UserInfoEntity","api":[{"method":"post","path":"/delete"},{"method":"post","path":"/update"},{"method":"get","path":"/info"},{"method":"post","path":"/list"},{"method":"post","path":"/page"},{"method":"post","path":"/add"}]}]